<?xml version="1.0" encoding="GB2312"?>
    <?xml:stylesheet type="text/xsl" href="/xsl/xsl_c/interfaceman.xsl"?>    <manpage>
    <volume>短信彩信引擎</volume>
    <interface> ISmsData </interface>
    <description>
        <para>
            提供短信数据的操作，继承自            <link url="IMessageData.htm">            IMessageData            </link>            接口。
        </para>
    </description>
    <methods>
<parent>
<interface_name>IMessageData</interface_name><interface_url>IMessageData</interface_url>    <method>
        <method_name>SetMessageId</method_name>
        <method_url>..\interface\IMessageData\SetMessageId</method_url>
    <m_description>
            设置信息的索引。
    </m_description>
    </method>
    <method>
        <method_name>GetMessageId</method_name>
        <method_url>..\interface\IMessageData\GetMessageId</method_url>
    <m_description>
            获取信息的索引。
    </m_description>
    </method>
    <method>
        <method_name>SetMessageBoxId</method_name>
        <method_url>..\interface\IMessageData\SetMessageBoxId</method_url>
    <m_description>
            设置信息所在信息箱的索引。
    </m_description>
    </method>
    <method>
        <method_name>GetMessageBoxId</method_name>
        <method_url>..\interface\IMessageData\GetMessageBoxId</method_url>
    <m_description>
            获取信息所在信息箱的索引。
    </m_description>
    </method>
    <method>
        <method_name>SetMessageTime</method_name>
        <method_url>..\interface\IMessageData\SetMessageTime</method_url>
    <m_description>
            设置信息的存储、发送或接收时间。
    </m_description>
    </method>
    <method>
        <method_name>GetMessageTime</method_name>
        <method_url>..\interface\IMessageData\GetMessageTime</method_url>
    <m_description>
            获取信息的存储、发送或接收时间。
    </m_description>
    </method>
    <method>
        <method_name>SetMessageType</method_name>
        <method_url>..\interface\IMessageData\SetMessageType</method_url>
    <m_description>
            设置信息的信息类型。
    </m_description>
    </method>
    <method>
        <method_name>GetMessageType</method_name>
        <method_url>..\interface\IMessageData\GetMessageType</method_url>
    <m_description>
            获取信息的信息类型。
    </m_description>
    </method>
    <method>
        <method_name>SetMessageStatus</method_name>
        <method_url>..\interface\IMessageData\SetMessageStatus</method_url>
    <m_description>
            设置信息的信息状态。
    </m_description>
    </method>
    <method>
        <method_name>GetMessageStatus</method_name>
        <method_url>..\interface\IMessageData\GetMessageStatus</method_url>
    <m_description>
            获取信息的信息状态。
    </m_description>
    </method>
    <method>
        <method_name>SetAddress</method_name>
        <method_url>..\interface\IMessageData\SetAddress</method_url>
    <m_description>
            设置信息的地址。
    </m_description>
    </method>
    <method>
        <method_name>GetAddress</method_name>
        <method_url>..\interface\IMessageData\GetAddress</method_url>
    <m_description>
            获取信息的地址。
    </m_description>
    </method>
    <method>
        <method_name>GetAddressSize</method_name>
        <method_url>..\interface\IMessageData\GetAddressSize</method_url>
    <m_description>
            获取信息地址的大小。
    </m_description>
    </method>
    <method>
        <method_name>SetIconName</method_name>
        <method_url>..\interface\IMessageData\SetIconName</method_url>
    <m_description>
            设置信息的图标名称。
    </m_description>
    </method>
    <method>
        <method_name>GetIconName</method_name>
        <method_url>..\interface\IMessageData\GetIconName</method_url>
    <m_description>
            获取信息的图标名称。
    </m_description>
    </method>
</parent>
<self>
    <method>
        <method_name>SetSimIndex</method_name>
        <method_url>..\interface\ISmsData\SetSimIndex</method_url>
    <m_description>
            设置SIM卡短信的索引。
    </m_description>
    </method>
    <method>
        <method_name>GetSimIndex</method_name>
        <method_url>..\interface\ISmsData\GetSimIndex</method_url>
    <m_description>
            获取sim卡短信的索引。
    </m_description>
    </method>
    <method>
        <method_name>SetContent</method_name>
        <method_url>..\interface\ISmsData\SetContent</method_url>
    <m_description>
            设置短信的内容。
    </m_description>
    </method>
    <method>
        <method_name>GetContent</method_name>
        <method_url>..\interface\ISmsData\GetContent</method_url>
    <m_description>
            获取短信的内容。
    </m_description>
    </method>
    <method>
        <method_name>GetContentSize</method_name>
        <method_url>..\interface\ISmsData\GetContentSize</method_url>
    <m_description>
            获取短信内容的大小。
    </m_description>
    </method>
</self>
    </methods>
    <requirements>
        <system>
            <system_name>
《Elastos 2.0》或更高版本            </system_name>
        </system>
        <headerfile>
            <file_name>elatype.h、stdlib.h、mmsdef.h、MessageData.h、CSmsData.h、_CSmsData.h</file_name>
        </headerfile>
        <library>
            <lib_name>ElDatabase.lib、elastos.lib、ElCRuntime.lib、ElUtilities.lib</lib_name>
        </library>
    </requirements>
</manpage>