<!--==========================================================================-->
<!-- Copyright (c) 2000-2004,  Elastos, Inc.  All Rights Reserved.-->
<!--==========================================================================-->

    <?xml version = "1.0" encoding="GB2312" ?>
    <?xml:stylesheet type="text/xsl" href="/xsl/xsl_e/methodmanual.xsl"?><manpage>
<volume>System COM Interface </volume>
<interface>ICondition</interface><method> PulseAll </method>
    <description>
        <para>
        	Wakes up all the waiting threads.
        </para>
    </description>
    <syntax>
        <return_val> ECODE </return_val>
    </syntax>

		<return>
		<para> Returns NOERROR if the functiion succeeds </para>
		    <para>See <link url="..\..\..\..\reference\basic_data_type\hresult.htm">ECODE</link> for related help.</para>
    </return>

	<remarks>
		<para>
			This method wakes up all the waiting threads. If no thread is waiting for the <b>Condition</b> object, 
			the method does nothing.
		</para>
	</remarks>

    <requirements>
        <system>
            <system_name>
				Windows 2000 or later; Elastos 2.0 or later.
	    	</system_name>
        </system>
    </requirements>
</manpage>