

<?xml version = "1.0" encoding="GB2312" ?>
<?xml:stylesheet type="text/xsl" href="/xsl/xsl_c/methodmanual.xsl"?>

<manpage>
    <sample url="sdk\eztypes\AStringBuf\Append">Append</sample>
    <volume> 常用数据结构 </volume>
    <interface> AStringBuf  </interface>
    <method> Append </method>

    <description>
        <para>在AStringBuf对象中原字符串末尾追加另一指定字符。</para>
    </description>

    <syntax>
        <return_val> AStringBuf &amp;</return_val>
        <parameters>
        <api_param>
            <param_type>AChar</param_type>
            <param_name>ac</param_name>
            <param_note>
                <para> AChar型字符。 </para>
            </param_note>
        </api_param>
        </parameters>
    </syntax>

    <return>
        <para>返回AStringBuf对象引用。</para>
    </return>

    

</manpage>