    <?xml version = "1.0" encoding="GB2312" ?>
    <?xml:stylesheet type="text/xsl" href="/xsl/xsl_c/custom_type.xsl"?>    <manpage>
    <volume>通讯引擎</volume>
    <types> TAPITIME </types>
    <description>
        <para>
            TAPI时间
        </para>
    </description>
  <struct>
        <struct_member>
            <mem_type>WORD</mem_type>
            <mem_name>wYear</mem_name>
            <mem_description>年 </mem_description>
        </struct_member>
        <struct_member>
            <mem_type>WORD</mem_type>
            <mem_name>wMonth</mem_name>
            <mem_description>月 </mem_description>
        </struct_member>
        <struct_member>
            <mem_type>WORD</mem_type>
            <mem_name>wDay</mem_name>
            <mem_description>日</mem_description>
        </struct_member>
        <struct_member>
            <mem_type>WORD</mem_type>
            <mem_name> wHour </mem_name>
            <mem_description>时 </mem_description>
        </struct_member>
         <struct_member>
            <mem_type>WORD</mem_type>
            <mem_name>wMinute</mem_name>
            <mem_description>分</mem_description>
        </struct_member>
         <struct_member>
            <mem_type>WORD</mem_type>
            <mem_name>wSecond</mem_name>
            <mem_description>秒</mem_description>
        </struct_member>
         <struct_member>
            <mem_type>WORD</mem_type>
            <mem_name>wMilliseconds</mem_name>
            <mem_description>微秒</mem_description>
        </struct_member>
    </struct>



</manpage>