<?xml version = "1.0" encoding="GB2312" ?>
    <?xml:stylesheet type="text/xsl" href="/xsl/xsl_c/interfaceman.xsl"?>    <manpage>
    <volume></volume>
    <Interface> ICarArraySetter </Interface>
    <description>
        <para>
             CarArray变量赋值接口
        </para>
    </description>
    <methods>
<self>

    <method>
        <method_name>SetUsed</method_name>
        <method_url>..\Interface\ICarArraySetter\SetUsed</method_url>
    <m_description>
设置该变量的空间用量。
    </m_description>
    </method>
    <method>
        <method_name>SetInt16Element</method_name>
        <method_url>..\Interface\ICarArraySetter\SetInt16Element</method_url>
    <m_description>
通过序号设置Int16类型的元素值。
    </m_description>
    </method>
    <method>
        <method_name>SetInt32Element</method_name>
        <method_url>..\Interface\ICarArraySetter\SetInt32Element</method_url>
    <m_description>
通过序号设置Int32类型的元素值。
    </m_description>
    </method>
    <method>
        <method_name>SetInt64Element</method_name>
        <method_url>..\Interface\ICarArraySetter\SetInt64Element</method_url>
    <m_description>
通过序号设置Int64类型的元素值。
    </m_description>
    </method>
    <method>
        <method_name>SetByteElement</method_name>
        <method_url>..\Interface\ICarArraySetter\SetByteElement</method_url>
    <m_description>
通过序号设置Byte类型的元素值。
    </m_description>
    </method>
    <method>
        <method_name>SetFloatElement</method_name>
        <method_url>..\Interface\ICarArraySetter\SetFloatElement</method_url>
    <m_description>
通过序号设置Float类型的元素值。
    </m_description>
    </method>
    <method>
        <method_name>SetDoubleElement</method_name>
        <method_url>..\Interface\ICarArraySetter\SetDoubleElement</method_url>
    <m_description>
通过序号设置Double类型的元素值。
    </m_description>
    </method>
    <method>
        <method_name>SetACharElement</method_name>
        <method_url>..\Interface\ICarArraySetter\SetACharElement</method_url>
    <m_description>
通过序号设置AChar类型的元素值。
    </m_description>
    </method>
    <method>
        <method_name>SetWCharElement</method_name>
        <method_url>..\Interface\ICarArraySetter\SetWCharElement</method_url>
    <m_description>
通过序号设置WChar类型的元素值。
    </m_description>
    </method>
    <method>
        <method_name>SetAStringElement</method_name>
        <method_url>..\Interface\ICarArraySetter\SetAStringElement</method_url>
    <m_description>
通过序号设置AString类型的元素值。
    </m_description>
    </method>
    <method>
        <method_name>SetWStringElement</method_name>
        <method_url>..\Interface\ICarArraySetter\SetWStringElement</method_url>
    <m_description>
通过序号设置WString类型的元素值。
    </m_description>
    </method>
    <method>
        <method_name>SetBooleanElement</method_name>
        <method_url>..\Interface\ICarArraySetter\SetBooleanElement</method_url>
    <m_description>
通过序号设置Boolean类型的元素值。
    </m_description>
    </method>
    <method>
        <method_name>SetEMuidElement</method_name>
        <method_url>..\Interface\ICarArraySetter\SetEMuidElement</method_url>
    <m_description>
通过序号设置IID类型的元素值。
    </m_description>
    </method>
    <method>
        <method_name>SetEGuidElement</method_name>
        <method_url>..\Interface\ICarArraySetter\SetEGuidElement</method_url>
    <m_description>
通过序号设置ClassID类型的元素值。
    </m_description>
    </method>
    <method>
        <method_name>SetECodeElement</method_name>
        <method_url>..\Interface\ICarArraySetter\SetECodeElement</method_url>
    <m_description>
通过序号设置ECode类型的元素值。
    </m_description>
    </method>
    <method>
        <method_name>SetLocalTypeElement</method_name>
        <method_url>..\Interface\ICarArraySetter\SetLocalTypeElement</method_url>
    <m_description>
通过序号设置自定义类型的元素的值。
    </m_description>
    </method>
    <method>
        <method_name>SetObjectPtrElement</method_name>
        <method_url>..\Interface\ICarArraySetter\SetObjectPtrElement</method_url>
    <m_description>
通过序号设置PObject类型的元素值。
    </m_description>
    </method>
    <method>
        <method_name>GetStructElementSetter</method_name>
        <method_url>..\Interface\ICarArraySetter\GetStructElementSetter</method_url>
    <m_description>
通过序号获取结构体的Setter。
    </m_description>
    </method>
    <method>
        <method_name>GetEnumSetter</method_name>
        <method_url>..\Interface\ICarArraySetter\GetEnumSetter</method_url>
    <m_description>
通过序号设置枚举类型的值。
    </m_description>
    </method>
    
</self>
    </methods>
    <requirements>
        <system>
            <system_name>
Elastos操作系统       </system_name>
        </system>
    </requirements>
</manpage>