<?xml version = "1.0" encoding="GB2312" ?>
    <?xml:stylesheet type="text/xsl" href="/xsl/xsl_c/interfaceman.xsl"?>    <manpage>
    <volume></volume>
    <Interface> ITypeAliasInfo </Interface>
    <description>
        <para>
            类型别名信息接口
        </para>
    </description>
    <methods>
<self>
    <method>
        <method_name>GetName</method_name>
        <method_url>..\Interface\ITypeAliasInfo\GetName</method_url>
    <m_description>
获取类型别名。
    </m_description>
    </method>
    <method>
        <method_name>GetTypeInfo</method_name>
        <method_url>..\Interface\ITypeAliasInfo\GetTypeInfo</method_url>
    <m_description>
获取类型别名信息。
    </m_description>
    </method>
    <method>
        <method_name>GetModuleInfo</method_name>
        <method_url>..\Interface\ITypeAliasInfo\GetModuleInfo</method_url>
    <m_description>
获取构件信息。
    </m_description>
    </method>
    <method>
        <method_name>IsDummy</method_name>
        <method_url>..\Interface\ITypeAliasInfo\IsDummy</method_url>
    <m_description>
判断是否为哑元。
    </m_description>
    </method>
    <method>
        <method_name>GetPtrLevel</method_name>
        <method_url>..\Interface\ITypeAliasInfo\GetPtrLevel</method_url>
    <m_description>
获得指针的层级。
    </m_description>
    </method>
</self>
    </methods>
    <requirements>
        <system>
            <system_name>
Elastos操作系统            </system_name>
        </system>
    </requirements>
</manpage>