<?xml version = "1.0" encoding="GB2312" ?>
    <?xml:stylesheet type="text/xsl" href="/xsl/xsl_c/interfaceman.xsl"?>   
<manpage>
    <volume> IVariableOfWStringBuf接口</volume>
    <interface>  IVariableOfWStringBuf</interface>
    <description>
        <para>
              IVariableOfWStringBuf接口
        </para>
    </description>
    <methods>

<self>
    <method>
        <method_name>GetSetter</method_name>
        <method_url>..\Interface\IVariableOfWStringBuf\GetSetter</method_url>
    <m_description>
获取setter接口
    </m_description>
    </method>
    <method>
        <method_name>GetGetter</method_name>
        <method_url>..\Interface\IVariableOfWStringBuf\GetGetter</method_url>
    <m_description>
获取getter接口
    </m_description> 
    </method>   
</self>
    </methods>
    <remarks>
    	<para>IVariableOfWStringBuf定义:interface IVariableOfWStringBuf : <link url="IVariable.htm">IVariable</link></para>
    </remarks>      
</manpage>