<?xml version="1.0" encoding="GB2312"?>
    <?xml:stylesheet type="text/xsl" href="/xsl/xsl_c/methodmanual.xsl"?><manpage>
<volume>地址簿引擎</volume>
<interface>IAddressBook</interface><method> GetEntityById </method>
    <description>
        <para>
            通过指定的记录ID，查找相应的记录。
        </para>
    </description>
    <syntax>
        <return_val> ECODE </return_val>
        <parameters>
            <api_param>
                <param_inout>[in]</param_inout>
                <param_type> ENTITY_CLASS </param_type>
                <param_name> ecEntity </param_name>
                <param_note>
                    <para>
指定记录的类型，参见数据结构<link url="../../datatype/_ENTITY_CLASS.htm">ENTITY_CLASS</link>                    </para>
                </param_note>
            </api_param>
            <api_param>
                <param_inout>[in]</param_inout>
                <param_type> long </param_type>
                <param_name> lEntityId </param_name>
                <param_note>
                    <para>
指定记录的ID                    </para>
                </param_note>
            </api_param>
            <api_param>
                <param_inout>[out]</param_inout>
                <param_type> IEntityRef * </param_type>
                <param_name> ppiEntity </param_name>
                <param_note>
                    <para>
指向IEntity接口指针的指针，用于获取返回的记录接口指针                    </para>
                </param_note>
            </api_param>
        </parameters>
    </syntax>

<return>
    <para>
            如果方法调用成功，返回S_OK；如果输入的参数无效或ppiEntity为NULL，返回E_INVALIDARG。</para><para>            其他参见            <link url="../../ab_error.htm">            地址簿错误返回值列表            </link>            。    </para>
</return>
    <requirements>
        <system>
            <system_name>
《Elastos 2.0》或更高版本            </system_name>
        </system>
        <dll>
            <dll_name>database.dll</dll_name>
        </dll>
        <headerfile>
            <file_name>CAddressBook.h, CDBStore.h, CSimStore.h, CContact.h, CContactGroup.h,  Abdata.h, spcomm.h</file_name>
        </headerfile>
        <library>
            <lib_name>ElCRuntime.lib, elastos.lib, utility.lib</lib_name>
        </library>
    </requirements>
    <references>
        <reference>
            <ref_name>GetEntityByName</ref_name>
            <ref_url>GetEntityByName</ref_url>
        </reference>
    </references>
</manpage>