<?xml version="1.0" encoding="GB2312"?>
    <?xml:stylesheet type="text/xsl" href="/xsl/xsl_c/custom_type.xsl"?>    <manpage>
    <volume>照相摄像引擎模块</volume>
    <types> CamMode </types>
    <description>
        <para>
            相机模式枚举类型
        </para>
    </description>
<enum>    <enum_member>    <mem_name> CamMode_Preview </mem_name>    <mem_value> 0x0 </mem_value>    <mem_description>        预览模式    </mem_description>    </enum_member>    <enum_member>    <mem_name> CamMode_Video </mem_name>    <mem_value> 0x1 </mem_value>    <mem_description>        摄像模式    </mem_description>    </enum_member></enum></manpage>